vendas_analise/__init__.py
vendas_analise/vendas.py
vendas_analise-0.0.1.dist-info/METADATA
vendas_analise-0.0.1.dist-info/WHEEL
vendas_analise-0.0.1.dist-info/top_level.txt
vendas_analise-0.0.1.dist-info/RECORD
