Metadata-Version: 2.1
Name: vendas-analise
Version: 0.0.1
Summary: Um pacote para análise de vendas
Home-page: https://github.com/luiz-vaz/vendas_analise_package
Author: Luiz Vaz
Author-email: luiz.henrique.vaz@hotmail.com
